{
    "meta": {
        "version": "1.0",
        "type": "user_composition",
        "test_name": "TESTONE",
        "created_by": "robot_app",
        "created_at": "2025-05-29T14:17:56.718643",
        "description": "Generated test composition: TESTONE"
    },
    "selected_settings": {
        "documentation": "TESTONE",
        "libraries": [
            {
                "library_name": "Lib.CommonLibrary",
                "category": "common",
                "config": {}
            }
        ],
        "suite_setup": null,
        "suite_teardown": null
    },
    "selected_variables": [
        {
            "name": "TIMEOUT",
            "value": "30s",
            "data_type": "string"
        }
    ],
    "individual_testcases": [
        {
            "test_id": 1989532173184,
            "test_name": "Execute Keyword - start_listening [id]1989532173184",
            "type": "keyword",
            "keyword_name": "start_listening",
            "keyword_category": "common",
            "priority": "optional",
            "description": "開始監聽設備訊息",
            "parameters": {}
        },
        {
            "test_id": 1989532179136,
            "test_name": "Execute Keyword - send_can_message [id]1989532179136",
            "type": "keyword",
            "keyword_name": "send_can_message",
            "keyword_category": "common",
            "priority": "optional",
            "description": "Sends a CAN message using the specified CAN ID, payload, and other parameters.",
            "parameters": {
                "can_id": "\"300\"",
                "payload": "\"30303030\"",
                "node": "1",
                "can_type": "0"
            }
        },
        {
            "test_id": 1989532187968,
            "test_name": "Execute Keyword - delay [id]1989532187968",
            "type": "keyword",
            "keyword_name": "delay",
            "keyword_category": "common",
            "priority": "optional",
            "description": "暫停執行指定的秒數（非阻塞實現） 參數: seconds: 暫停的秒數，可以是整數或浮點數 reason: 可選參數，記錄暫停原因",
            "parameters": {
                "seconds": "10",
                "reason": "None"
            }
        },
        {
            "test_id": 1989532275904,
            "test_name": "Execute Keyword - stop_listening [id]1989532275904",
            "type": "keyword",
            "keyword_name": "stop_listening",
            "keyword_category": "common",
            "priority": "optional",
            "description": "停止監聽設備訊息",
            "parameters": {}
        }
    ],
    "keyword_dependencies": [
        {
            "category": "common",
            "library_name": "Lib.CommonLibrary",
            "required_keywords": []
        }
    ],
    "runtime_config": {
        "output_filename": "TESTONE.robot",
        "execution_mode": "multiple_tests",
        "parallel": false,
        "tags_to_run": [
            "auto-generated"
        ],
        "variables_file": null
    }
}